ngin/__init__.py
ngin/command_pb2.py
ngin/ngin.py
ngin/plane.py
ngin-0.6.dist-info/LICENSE
ngin-0.6.dist-info/METADATA
ngin-0.6.dist-info/WHEEL
ngin-0.6.dist-info/top_level.txt
ngin-0.6.dist-info/RECORD
